__init__.py
_version.py
bcv_api.py
bcv_api-1.0.3.dist-info/COPYING
bcv_api-1.0.3.dist-info/LICENSE
bcv_api-1.0.3.dist-info/METADATA
bcv_api-1.0.3.dist-info/WHEEL
bcv_api-1.0.3.dist-info/top_level.txt
bcv_api-1.0.3.dist-info/RECORD
