Metadata-Version: 2.1
Name: bcv-api
Version: 1.0.3
Summary: Parses BCV html to get prices of currencies in VEF
Author-email: sivefunc <sivefunc@tuta.io>
License: bcv-api small library that access BCV to get prices of currencies.
Project-URL: Homepage, https://gitlab.com/sivefunc/bcv-api
Keywords: bcv,exchange,api,venezuela,http
Classifier: License :: OSI Approved :: GNU General Public License v3 (GPLv3)
Classifier: Programming Language :: Python
Classifier: Programming Language :: Python :: 3
Requires-Python: >=3.9
License-File: LICENSE
License-File: COPYING
Requires-Dist: requests>=2.32.3
